rtl/pt_memory_model.v
module pt_memory_model
(
    input  wire        clk,
    input  wire        rst_n,

    //-----------------------------------------
    // PTW Interface
    //-----------------------------------------

    input  wire        mem_req,
    input  wire [31:0] mem_addr,

    output reg         mem_ready,
    output reg [31:0]  mem_rdata
);

localparam DEPTH = 64;

reg [31:0] mem [0:DEPTH-1];

integer i;

wire [5:0] word_index;

/*
    PTW generates:

    pte_addr = satp_base + vpn*4

    Since this is a small simulation model,
    we only use lower address bits.
*/

assign word_index = mem_addr[7:2];

always @(posedge clk or negedge rst_n)
begin

    if(!rst_n)
    begin

        mem_ready <= 1'b0;
        mem_rdata <= 32'd0;

        //-------------------------------------
        // Clear memory
        //-------------------------------------

        for(i=0;i<DEPTH;i=i+1)
        begin
            mem[i] <= 32'd0;
        end

        //-------------------------------------
        // Sample Page Table Entries
        //-------------------------------------

        /*
            VPN 0
            PFN = 0x10000
            V R W X U = 1
        */

        mem[0] <=
        {
            20'h10000,
            2'b00,
            1'b1, // U
            1'b1, // X
            1'b1, // W
            1'b1, // R
            1'b1, // V
            5'b00000
        };

        /*
            VPN 1
            Read Only
        */

        mem[1] <=
        {
            20'h10001,
            2'b00,
            1'b1,
            1'b0,
            1'b0,
            1'b1,
            1'b1,
            5'b00000
        };

        /*
            VPN 2
            Invalid Page
        */

        mem[2] <=
        {
            20'h10002,
            2'b00,
            1'b1,
            1'b1,
            1'b1,
            1'b1,
            1'b0,
            5'b00000
        };

        /*
            VPN 3
            Supervisor Only
        */

        mem[3] <=
        {
            20'h10003,
            2'b00,
            1'b0,
            1'b1,
            1'b1,
            1'b1,
            1'b1,
            5'b00000
        };

    end
    else
    begin

        mem_ready <= 1'b0;

        //-------------------------------------
        // Single-cycle BRAM Read
        //-------------------------------------

        if(mem_req)
        begin

            mem_rdata <= mem[word_index];

            mem_ready <= 1'b1;

        end

    end

end

endmodule

rtl/address_translator.v
module address_translator
(
    input  wire [19:0] pfn,
    input  wire [11:0] page_offset,

    output wire [31:0] physical_addr
);

assign physical_addr =
{
    pfn,
    page_offset
};

endmodule

rtl/permission_checker.v
module permission_checker
(
    input wire [1:0] access_type,
    input wire user_mode,

    input wire pte_valid,
    input wire pte_r,
    input wire pte_w,
    input wire pte_x,
    input wire pte_u,

    output reg access_granted,

    output reg page_fault,
    output reg read_fault,
    output reg write_fault,
    output reg execute_fault,
    output reg user_fault
);

always @(*)
begin

    access_granted = 0;

    page_fault = 0;
    read_fault = 0;
    write_fault = 0;
    execute_fault = 0;
    user_fault = 0;

    if(!pte_valid)
    begin
        page_fault = 1;
    end
    else if(user_mode && !pte_u)
    begin
        user_fault = 1;
    end
    else
    begin

        case(access_type)

            2'b00:
            begin
                if(pte_r)
                    access_granted = 1;
                else
                    read_fault = 1;
            end

            2'b01:
            begin
                if(pte_w)
                    access_granted = 1;
                else
                    write_fault = 1;
            end

            2'b10:
            begin
                if(pte_x)
                    access_granted = 1;
                else
                    execute_fault = 1;
            end

        endcase
    end
end

endmodule

rtl/ptw_fsm.v
module ptw_fsm
(
    input wire clk,
    input wire rst_n,

    //------------------------------------------------
    // PTW Request
    //------------------------------------------------

    input wire start_walk,

    input wire [31:0] satp_base,
    input wire [19:0] vpn,

    //------------------------------------------------
    // Memory Interface
    //------------------------------------------------

    output reg        mem_req,
    output reg [31:0] mem_addr,

    input wire        mem_ready,
    input wire [31:0] mem_rdata,

    //------------------------------------------------
    // Refill Outputs
    //------------------------------------------------

    output reg        refill_valid,

    output reg [19:0] refill_vpn,
    output reg [19:0] refill_pfn,

    output reg        refill_v,
    output reg        refill_r,
    output reg        refill_w,
    output reg        refill_x,
    output reg        refill_u,

    //------------------------------------------------
    // Status
    //------------------------------------------------

    output reg done,
    output reg page_fault
);

localparam IDLE      = 2'b00;
localparam REQUEST   = 2'b01;
localparam CHECK_PTE = 2'b10;
localparam COMPLETE  = 2'b11;

reg [1:0] state;

always @(posedge clk or negedge rst_n)
begin

    if(!rst_n)
    begin

        state <= IDLE;

        mem_req <= 0;
        mem_addr <= 0;

        refill_valid <= 0;

        refill_vpn <= 0;
        refill_pfn <= 0;

        refill_v <= 0;
        refill_r <= 0;
        refill_w <= 0;
        refill_x <= 0;
        refill_u <= 0;

        done <= 0;
        page_fault <= 0;

    end
    else
    begin

        refill_valid <= 0;
        done <= 0;

        case(state)

        //--------------------------------------------
        // IDLE
        //--------------------------------------------

        IDLE:
        begin

            page_fault <= 0;

            if(start_walk)
            begin

                mem_addr <= satp_base + {vpn,2'b00};

                mem_req <= 1'b1;

                state <= REQUEST;

            end

        end

        //--------------------------------------------
        // WAIT FOR MEMORY
        //--------------------------------------------

        REQUEST:
        begin

            if(mem_ready)
            begin

                mem_req <= 0;

                state <= CHECK_PTE;

            end

        end

        //--------------------------------------------
        // DECODE PTE
        //--------------------------------------------

        CHECK_PTE:
        begin

            if(mem_rdata[5] == 1'b0)
            begin

                page_fault <= 1'b1;

                state <= COMPLETE;

            end
            else
            begin

                refill_vpn <= vpn;

                refill_pfn <= mem_rdata[31:12];

                refill_u <= mem_rdata[9];
                refill_x <= mem_rdata[8];
                refill_w <= mem_rdata[7];
                refill_r <= mem_rdata[6];
                refill_v <= mem_rdata[5];

                refill_valid <= 1'b1;

                state <= COMPLETE;

            end

        end

        //--------------------------------------------
        // COMPLETE
        //--------------------------------------------

        COMPLETE:
        begin

            done <= 1'b1;

            state <= IDLE;

        end

        endcase

    end

end

endmodule

rtl/tlb_4way_plru.v
module tlb_4way_plru
#(
    parameter VPN_WIDTH  = 20,
    parameter PFN_WIDTH  = 20,
    parameter ASID_WIDTH = 8,
    parameter NUM_SETS   = 4
)
(
    input wire clk,
    input wire rst_n,

    // Lookup Port
    input wire lookup_valid,
    input wire [VPN_WIDTH-1:0] lookup_vpn,
    input wire [ASID_WIDTH-1:0] lookup_asid,

    output reg hit,
    output reg [PFN_WIDTH-1:0] hit_pfn,

    // Refill Port
    input wire refill_valid,
    input wire [VPN_WIDTH-1:0] refill_vpn,
    input wire [ASID_WIDTH-1:0] refill_asid,
    input wire [PFN_WIDTH-1:0] refill_pfn
);

integer i,j;

reg valid_mem [0:NUM_SETS-1][0:3];

reg [VPN_WIDTH-1:0] vpn_mem [0:NUM_SETS-1][0:3];
reg [PFN_WIDTH-1:0] pfn_mem [0:NUM_SETS-1][0:3];
reg [ASID_WIDTH-1:0] asid_mem [0:NUM_SETS-1][0:3];

reg [1:0] replace_ptr [0:NUM_SETS-1];

wire [1:0] lookup_set;
wire [1:0] refill_set;

assign lookup_set = lookup_vpn[1:0];
assign refill_set = refill_vpn[1:0];

reg [3:0] way_hit;
reg [1:0] hit_way;

always @(*)
begin

    way_hit[0] =
        valid_mem[lookup_set][0] &&
        (vpn_mem[lookup_set][0] == lookup_vpn) &&
        (asid_mem[lookup_set][0] == lookup_asid);

    way_hit[1] =
        valid_mem[lookup_set][1] &&
        (vpn_mem[lookup_set][1] == lookup_vpn) &&
        (asid_mem[lookup_set][1] == lookup_asid);

    way_hit[2] =
        valid_mem[lookup_set][2] &&
        (vpn_mem[lookup_set][2] == lookup_vpn) &&
        (asid_mem[lookup_set][2] == lookup_asid);

    way_hit[3] =
        valid_mem[lookup_set][3] &&
        (vpn_mem[lookup_set][3] == lookup_vpn) &&
        (asid_mem[lookup_set][3] == lookup_asid);

end

always @(*)
begin

    hit = |way_hit;

    hit_way = 2'd0;

    if(way_hit[0])
        hit_way = 2'd0;
    else if(way_hit[1])
        hit_way = 2'd1;
    else if(way_hit[2])
        hit_way = 2'd2;
    else if(way_hit[3])
        hit_way = 2'd3;

    hit_pfn = 0;

    if(hit)
        hit_pfn = pfn_mem[lookup_set][hit_way];

end

always @(posedge clk or negedge rst_n)
begin

    if(!rst_n)
    begin

        for(i=0;i<NUM_SETS;i=i+1)
        begin

            replace_ptr[i] <= 0;

            for(j=0;j<4;j=j+1)
            begin
                valid_mem[i][j] <= 0;
            end

        end

    end
    else
    begin

        if(refill_valid)
        begin

            valid_mem[refill_set][replace_ptr[refill_set]]
                <= 1'b1;

            vpn_mem[refill_set][replace_ptr[refill_set]]
                <= refill_vpn;

            asid_mem[refill_set][replace_ptr[refill_set]]
                <= refill_asid;

            pfn_mem[refill_set][replace_ptr[refill_set]]
                <= refill_pfn;

            replace_ptr[refill_set]
                <= replace_ptr[refill_set] + 1'b1;

        end

    end

end

endmodule

rtl/csr_registers.v
module csr_registers
(
    input  wire        clk,
    input  wire        rst_n,

    input  wire        csr_we,
    input  wire [1:0]  csr_addr,
    input  wire [31:0] csr_wdata,

    output reg [31:0] satp_base,
    output reg [7:0]  asid,
    output reg        mmu_enable
);

always @(posedge clk or negedge rst_n)
begin
    if(!rst_n)
    begin
        satp_base <= 32'h1000_0000;
        asid      <= 8'd0;
        mmu_enable<= 1'b1;
    end
    else if(csr_we)
    begin
        case(csr_addr)

            2'b00:
                satp_base <= csr_wdata;

            2'b01:
                asid <= csr_wdata[7:0];

            2'b10:
                mmu_enable <= csr_wdata[0];

        endcase
    end
end

endmodule

rtl/mmu_top.v
module mmu_top
(
    input wire clk,
    input wire rst_n,

    //------------------------------------------------
    // CPU Interface
    //------------------------------------------------

    input wire req_valid,

    input wire [31:0] virtual_addr,

    input wire [1:0] access_type,
    input wire user_mode,

    //------------------------------------------------
    // Memory Interface
    //------------------------------------------------

    output wire mem_req,
    output wire [31:0] mem_addr,

    input wire mem_ready,
    input wire [31:0] mem_rdata,

    //------------------------------------------------
    // Outputs
    //------------------------------------------------

    output reg resp_valid,

    output reg [31:0] physical_addr,

    output wire page_fault,
    output wire read_fault,
    output wire write_fault,
    output wire execute_fault,
    output wire user_fault
);

localparam MMU_IDLE     = 2'b00;
localparam MMU_LOOKUP   = 2'b01;
localparam MMU_WAIT_PTW = 2'b10;

reg [1:0] state;

wire [19:0] vpn;
wire [11:0] page_offset;

assign vpn         = virtual_addr[31:12];
assign page_offset = virtual_addr[11:0];

wire [31:0] satp_base;
wire [7:0]  asid;
wire        mmu_enable;

csr_registers u_csr
(
    .clk(clk),
    .rst_n(rst_n),

    .csr_we(1'b0),
    .csr_addr(2'b00),
    .csr_wdata(32'd0),

    .satp_base(satp_base),
    .asid(asid),
    .mmu_enable(mmu_enable)
);

wire tlb_hit;
wire [19:0] tlb_pfn;

wire refill_valid;
wire [19:0] refill_vpn;
wire [19:0] refill_pfn;

wire refill_v;
wire refill_r;
wire refill_w;
wire refill_x;
wire refill_u;

tlb_4way_plru u_tlb
(
    .clk(clk),
    .rst_n(rst_n),

    .lookup_valid(req_valid),
    .lookup_vpn(vpn),
    .lookup_asid(asid),

    .hit(tlb_hit),
    .hit_pfn(tlb_pfn),

    .refill_valid(refill_valid),
    .refill_vpn(refill_vpn),
    .refill_asid(asid),
    .refill_pfn(refill_pfn)
);

wire ptw_done;

ptw_fsm u_ptw
(
    .clk(clk),
    .rst_n(rst_n),

    .start_walk(state == MMU_WAIT_PTW),

    .satp_base(satp_base),
    .vpn(vpn),

    .mem_req(mem_req),
    .mem_addr(mem_addr),

    .mem_ready(mem_ready),
    .mem_rdata(mem_rdata),

    .refill_valid(refill_valid),

    .refill_vpn(refill_vpn),
    .refill_pfn(refill_pfn),

    .refill_v(refill_v),
    .refill_r(refill_r),
    .refill_w(refill_w),
    .refill_x(refill_x),
    .refill_u(refill_u),

    .done(ptw_done),
    .page_fault(page_fault)
);

wire access_granted;

permission_checker u_perm
(
    .access_type(access_type),
    .user_mode(user_mode),

    .pte_valid(tlb_hit),

    .pte_r(1'b1),
    .pte_w(1'b1),
    .pte_x(1'b1),
    .pte_u(1'b1),

    .access_granted(access_granted),

    .page_fault(),
    .read_fault(read_fault),
    .write_fault(write_fault),
    .execute_fault(execute_fault),
    .user_fault(user_fault)
);

wire [31:0] translated_addr;

address_translator u_addr
(
    .pfn(tlb_pfn),
    .page_offset(page_offset),
    .physical_addr(translated_addr)
);

always @(posedge clk or negedge rst_n)
begin

    if(!rst_n)
    begin

        state <= MMU_IDLE;

        resp_valid <= 0;
        physical_addr <= 0;

    end
    else
    begin

        resp_valid <= 0;

        case(state)

        //------------------------------------
        // IDLE
        //------------------------------------

        MMU_IDLE:
        begin

            if(req_valid)
                state <= MMU_LOOKUP;

        end

        //------------------------------------
        // LOOKUP
        //------------------------------------

        MMU_LOOKUP:
        begin

            //--------------------------------
            // Bypass Mode
            //--------------------------------

            if(!mmu_enable)
            begin

                physical_addr <= virtual_addr;

                resp_valid <= 1;

                state <= MMU_IDLE;

            end

            //--------------------------------
            // TLB Hit
            //--------------------------------

            else if(tlb_hit && access_granted)
            begin

                physical_addr <= translated_addr;

                resp_valid <= 1;

                state <= MMU_IDLE;

            end

            //--------------------------------
            // TLB Miss
            //--------------------------------

            else
            begin

                state <= MMU_WAIT_PTW;

            end

        end

        //------------------------------------
        // WAIT FOR PTW
        //------------------------------------

        MMU_WAIT_PTW:
        begin

            if(ptw_done)
            begin

                state <= MMU_LOOKUP;

            end

        end

        endcase

    end

end

endmodule

tb/mmu_top_tb.v
`timescale 1ns/1ps

module mmu_top_tb;

reg clk;
reg rst_n;

// CPU Request Interface
reg         req_valid;
reg [31:0]  virtual_addr;
reg [1:0]   access_type;
reg         user_mode;

// DUT Outputs
wire        resp_valid;
wire [31:0] physical_addr;

wire page_fault;
wire read_fault;
wire write_fault;
wire execute_fault;
wire user_fault;

// Memory Interface
wire        mem_req;
wire [31:0] mem_addr;
wire        mem_ready;
wire [31:0] mem_rdata;

/////////////////////////////////////////////////
// DUT
/////////////////////////////////////////////////

mmu_top DUT
(
    .clk(clk),
    .rst_n(rst_n),

    .req_valid(req_valid),
    .virtual_addr(virtual_addr),

    .access_type(access_type),
    .user_mode(user_mode),

    .mem_req(mem_req),
    .mem_addr(mem_addr),

    .mem_ready(mem_ready),
    .mem_rdata(mem_rdata),

    .resp_valid(resp_valid),
    .physical_addr(physical_addr),

    .page_fault(page_fault),
    .read_fault(read_fault),
    .write_fault(write_fault),
    .execute_fault(execute_fault),
    .user_fault(user_fault)
);

/////////////////////////////////////////////////
// Page Table BRAM Model
/////////////////////////////////////////////////

pt_memory_model MEM
(
    .clk(clk),
    .rst_n(rst_n),

    .mem_req(mem_req),
    .mem_addr(mem_addr),

    .mem_ready(mem_ready),
    .mem_rdata(mem_rdata)
);

/////////////////////////////////////////////////
// Clock
/////////////////////////////////////////////////

always #5 clk = ~clk;

/////////////////////////////////////////////////
// Helper Task
/////////////////////////////////////////////////

task issue_request;

input [31:0] addr;
input [1:0] access;
input mode;

begin

    @(posedge clk);

    virtual_addr <= addr;
    access_type  <= access;
    user_mode    <= mode;

    req_valid <= 1'b1;

    @(posedge clk);

    req_valid <= 1'b0;

    repeat(10) @(posedge clk);

end

endtask

/////////////////////////////////////////////////
// Test Sequence
/////////////////////////////////////////////////

initial
begin

    $dumpfile("mmu.vcd");
    $dumpvars(0, mmu_top_tb);

    clk = 0;
    rst_n = 0;

    req_valid = 0;
    virtual_addr = 0;
    access_type = 0;
    user_mode = 0;

    //------------------------------------------------
    // Reset
    //------------------------------------------------

    #20;
    rst_n = 1;

    //------------------------------------------------
    // TEST 1
    // VPN 0
    // TLB MISS -> PTW REFILL
    //------------------------------------------------

    $display("");
    $display("TEST1 : TLB MISS / REFILL");

    issue_request(
        32'h0000_0123,
        2'b00,
        1'b1
    );

    //------------------------------------------------
    // TEST 2
    // SAME VPN
    // EXPECT TLB HIT
    //------------------------------------------------

    $display("");
    $display("TEST2 : TLB HIT");

    issue_request(
        32'h0000_0155,
        2'b00,
        1'b1
    );

    //------------------------------------------------
    // TEST 3
    // VPN1
    // READ ONLY PAGE
    // WRITE ACCESS
    //------------------------------------------------

    $display("");
    $display("TEST3 : WRITE FAULT");

    issue_request(
        32'h0000_1000,
        2'b01,
        1'b1
    );

    //------------------------------------------------
    // TEST 4
    // VPN2
    // INVALID PAGE
    //------------------------------------------------

    $display("");
    $display("TEST4 : PAGE FAULT");

    issue_request(
        32'h0000_2000,
        2'b00,
        1'b1
    );

    //------------------------------------------------
    // TEST 5
    // VPN3
    // SUPERVISOR PAGE
    // USER ACCESS
    //------------------------------------------------

    $display("");
    $display("TEST5 : USER FAULT");

    issue_request(
        32'h0000_3000,
        2'b00,
        1'b1
    );

    //------------------------------------------------
    // TEST 6
    // SUPERVISOR ACCESS
    //------------------------------------------------

    $display("");
    $display("TEST6 : SUPERVISOR ACCESS");

    issue_request(
        32'h0000_3000,
        2'b00,
        1'b0
    );

    //------------------------------------------------
    // TEST 7
    // EXECUTE ACCESS
    //------------------------------------------------

    $display("");
    $display("TEST7 : EXECUTE ACCESS");

    issue_request(
        32'h0000_0123,
        2'b10,
        1'b1
    );

    //------------------------------------------------
    // TEST 8
    // ASID Isolation Example
    //------------------------------------------------

    $display("");
    $display("TEST8 : ASID ISOLATION");

    DUT.u_csr.asid = 8'h01;

    issue_request(
        32'h0000_0123,
        2'b00,
        1'b1
    );

    DUT.u_csr.asid = 8'h02;

    issue_request(
        32'h0000_0123,
        2'b00,
        1'b1
    );

    //------------------------------------------------
    // TEST 9
    // MMU BYPASS MODE
    //------------------------------------------------

    $display("");
    $display("TEST9 : MMU BYPASS");

    DUT.u_csr.mmu_enable = 1'b0;

    issue_request(
        32'hDEAD_BEEF,
        2'b00,
        1'b1
    );

    //------------------------------------------------

    #100;

    $display("");
    $display("ALL TESTS COMPLETED");

    $finish;

end

/////////////////////////////////////////////////
// Monitor
/////////////////////////////////////////////////

always @(posedge clk)
begin

    if(resp_valid)
    begin

        $display(
            "TIME=%0t PA=%h PF=%b RF=%b WF=%b XF=%b UF=%b",
            $time,
            physical_addr,
            page_fault,
            read_fault,
            write_fault,
            execute_fault,
            user_fault
        );

    end

end

endmodule

mmu.vcd
$date
	Wed Jun 17 20:56:49 2026
$end
$version
	Icarus Verilog
$end
$timescale
	1ps
$end
$scope module mmu_top_tb $end
$var wire 1 ! write_fault $end
$var wire 1 " user_fault $end
$var wire 1 # resp_valid $end
$var wire 1 $ read_fault $end
$var wire 32 % physical_addr [31:0] $end
$var wire 1 & page_fault $end
$var wire 1 ' mem_req $end
$var wire 1 ( mem_ready $end
$var wire 32 ) mem_rdata [31:0] $end
$var wire 32 * mem_addr [31:0] $end
$var wire 1 + execute_fault $end
$var reg 2 , access_type [1:0] $end
$var reg 1 - clk $end
$var reg 1 . req_valid $end
$var reg 1 / rst_n $end
$var reg 1 0 user_mode $end
$var reg 32 1 virtual_addr [31:0] $end
$scope module DUT $end
$var wire 2 2 access_type [1:0] $end
$var wire 1 - clk $end
$var wire 1 . req_valid $end
$var wire 1 / rst_n $end
$var wire 1 0 user_mode $end
$var wire 32 3 virtual_addr [31:0] $end
$var wire 1 ! write_fault $end
$var wire 20 4 vpn [19:0] $end
$var wire 1 " user_fault $end
$var wire 32 5 translated_addr [31:0] $end
$var wire 20 6 tlb_pfn [19:0] $end
$var wire 1 7 tlb_hit $end
$var wire 32 8 satp_base [31:0] $end
$var wire 1 9 refill_x $end
$var wire 1 : refill_w $end
$var wire 20 ; refill_vpn [19:0] $end
$var wire 1 < refill_valid $end
$var wire 1 = refill_v $end
$var wire 1 > refill_u $end
$var wire 1 ? refill_r $end
$var wire 20 @ refill_pfn [19:0] $end
$var wire 1 $ read_fault $end
$var wire 1 A ptw_done $end
$var wire 12 B page_offset [11:0] $end
$var wire 1 & page_fault $end
$var wire 1 C mmu_enable $end
$var wire 1 ' mem_req $end
$var wire 1 ( mem_ready $end
$var wire 32 D mem_rdata [31:0] $end
$var wire 32 E mem_addr [31:0] $end
$var wire 1 + execute_fault $end
$var wire 8 F asid [7:0] $end
$var wire 1 G access_granted $end
$var parameter 2 H MMU_IDLE $end
$var parameter 2 I MMU_LOOKUP $end
$var parameter 2 J MMU_WAIT_PTW $end
$var reg 32 K physical_addr [31:0] $end
$var reg 1 # resp_valid $end
$var reg 2 L state [1:0] $end
$scope module u_addr $end
$var wire 12 M page_offset [11:0] $end
$var wire 32 N physical_addr [31:0] $end
$var wire 20 O pfn [19:0] $end
$upscope $end
$scope module u_csr $end
$var wire 1 - clk $end
$var wire 2 P csr_addr [1:0] $end
$var wire 32 Q csr_wdata [31:0] $end
$var wire 1 R csr_we $end
$var wire 1 / rst_n $end
$var reg 8 S asid [7:0] $end
$var reg 1 C mmu_enable $end
$var reg 32 T satp_base [31:0] $end
$upscope $end
$scope module u_perm $end
$var wire 2 U access_type [1:0] $end
$var wire 1 V pte_r $end
$var wire 1 W pte_u $end
$var wire 1 X pte_w $end
$var wire 1 Y pte_x $end
$var wire 1 0 user_mode $end
$var wire 1 7 pte_valid $end
$var reg 1 G access_granted $end
$var reg 1 + execute_fault $end
$var reg 1 Z page_fault $end
$var reg 1 $ read_fault $end
$var reg 1 " user_fault $end
$var reg 1 ! write_fault $end
$upscope $end
$scope module u_ptw $end
$var wire 1 - clk $end
$var wire 1 / rst_n $end
$var wire 32 [ satp_base [31:0] $end
$var wire 1 \ start_walk $end
$var wire 20 ] vpn [19:0] $end
$var wire 1 ( mem_ready $end
$var wire 32 ^ mem_rdata [31:0] $end
$var parameter 2 _ CHECK_PTE $end
$var parameter 2 ` COMPLETE $end
$var parameter 2 a IDLE $end
$var parameter 2 b REQUEST $end
$var reg 1 A done $end
$var reg 32 c mem_addr [31:0] $end
$var reg 1 ' mem_req $end
$var reg 1 & page_fault $end
$var reg 20 d refill_pfn [19:0] $end
$var reg 1 ? refill_r $end
$var reg 1 > refill_u $end
$var reg 1 = refill_v $end
$var reg 1 < refill_valid $end
$var reg 20 e refill_vpn [19:0] $end
$var reg 1 : refill_w $end
$var reg 1 9 refill_x $end
$var reg 2 f state [1:0] $end
$upscope $end
$scope module u_tlb $end
$var wire 1 - clk $end
$var wire 8 g lookup_asid [7:0] $end
$var wire 1 . lookup_valid $end
$var wire 20 h lookup_vpn [19:0] $end
$var wire 8 i refill_asid [7:0] $end
$var wire 20 j refill_pfn [19:0] $end
$var wire 1 < refill_valid $end
$var wire 20 k refill_vpn [19:0] $end
$var wire 1 / rst_n $end
$var wire 2 l refill_set [1:0] $end
$var wire 2 m lookup_set [1:0] $end
$var parameter 32 n ASID_WIDTH $end
$var parameter 32 o NUM_SETS $end
$var parameter 32 p PFN_WIDTH $end
$var parameter 32 q VPN_WIDTH $end
$var reg 1 7 hit $end
$var reg 20 r hit_pfn [19:0] $end
$var reg 2 s hit_way [1:0] $end
$var reg 4 t way_hit [3:0] $end
$var integer 32 u i [31:0] $end
$var integer 32 v j [31:0] $end
$upscope $end
$upscope $end
$scope module MEM $end
$var wire 1 - clk $end
$var wire 32 w mem_addr [31:0] $end
$var wire 1 ' mem_req $end
$var wire 1 / rst_n $end
$var wire 6 x word_index [5:0] $end
$var parameter 32 y DEPTH $end
$var reg 32 z mem_rdata [31:0] $end
$var reg 1 ( mem_ready $end
$var integer 32 { i [31:0] $end
$upscope $end
$scope task issue_request $end
$var reg 2 | access [1:0] $end
$var reg 32 } addr [31:0] $end
$var reg 1 ~ mode $end
$upscope $end
$upscope $end
$enddefinitions $end
$comment Show the parameter values. $end
$dumpall
b1000000 y
b10100 q
b10100 p
b100 o
b1000 n
b1 b
b0 a
b11 `
b10 _
b10 J
b1 I
b0 H
$end
#0
$dumpvars
x~
bx }
bx |
b1000000 {
b0 z
b0 x
b0 w
b100 v
b100 u
b0 t
b0 s
b0 r
b0 m
b0 l
b0 k
b0 j
b0 i
b0 h
b0 g
b0 f
b0 e
b0 d
b0 c
b0 ^
b0 ]
0\
b10000000000000000000000000000 [
1Z
1Y
1X
1W
1V
b0 U
b10000000000000000000000000000 T
b0 S
0R
b0 Q
b0 P
b0 O
b0 N
b0 M
b0 L
b0 K
0G
b0 F
b0 E
b0 D
1C
b0 B
0A
b0 @
0?
0>
0=
0<
b0 ;
0:
09
b10000000000000000000000000000 8
07
b0 6
b0 5
b0 4
b0 3
b0 2
b0 1
00
0/
0.
0-
b0 ,
0+
b0 *
b0 )
0(
0'
0&
b0 %
0$
0#
0"
0!
$end
#5000
b1000000 {
b100 v
b100 u
1-
#10000
0-
#15000
b100 v
b100 u
b1000000 {
1-
#20000
0-
1~
b0 |
b100100011 }
1/
#25000
1Z
b100100011 5
b100100011 N
b100100011 B
b100100011 M
1.
10
b100100011 1
b100100011 3
1-
#30000
0-
#35000
b1 L
0.
1-
#40000
0-
#45000
1\
b10 L
1-
#50000
0-
#55000
b1 f
1'
b10000000000000000000000000000 *
b10000000000000000000000000000 E
b10000000000000000000000000000 c
b10000000000000000000000000000 w
1-
#60000
0-
#65000
1(
b10000000000000000001111100000 )
b10000000000000000001111100000 D
b10000000000000000001111100000 ^
b10000000000000000001111100000 z
1-
#70000
0-
#75000
b10 f
0'
1(
1-
#80000
0-
#85000
0(
b11 f
1<
1=
1?
1:
19
1>
b10000000000000000 @
b10000000000000000 d
b10000000000000000 j
1-
#90000
0-
#95000
1G
0Z
b10000000000000000000100100011 5
b10000000000000000000100100011 N
b10000000000000000 6
b10000000000000000 O
b10000000000000000 r
17
b1 t
b0 f
1A
0<
1-
#100000
0-
#105000
0\
b1 L
b1 f
1'
0A
1-
#110000
0-
#115000
b0 L
1#
b10000000000000000000100100011 %
b10000000000000000000100100011 K
1(
1-
#120000
0-
#125000
1(
0#
b10 f
0'
1-
#130000
0-
#135000
b11 f
1<
0(
b101010101 }
1-
#140000
0-
#145000
b10000000000000000 6
b10000000000000000 O
b10000000000000000 r
b11 t
b10000000000000000000101010101 5
b10000000000000000000101010101 N
b101010101 B
b101010101 M
b0 f
1A
0<
1.
b101010101 1
b101010101 3
1-
#150000
0-
#155000
0A
b1 L
0.
1-
#160000
0-
#165000
b0 L
1#
b10000000000000000000101010101 %
b10000000000000000000101010101 K
1-
#170000
0-
#175000
0#
1-
#180000
0-
#185000
1-
#190000
0-
#195000
1-
#200000
0-
#205000
1-
#210000
0-
#215000
1-
#220000
0-
#225000
1-
#230000
0-
#235000
1-
#240000
0-
#245000
1-
#250000
0-
#255000
b1 |
b1000000000000 }
1-
#260000
0-
#265000
1Z
b0 6
b0 O
b0 r
07
b0 t
b1 m
0G
b1 4
b1 ]
b1 h
b0 5
b0 N
b0 B
b0 M
1.
b1 ,
b1 2
b1 U
b1000000000000 1
b1000000000000 3
1-
#270000
0-
#275000
b1 L
0.
1-
#280000
0-
#285000
1\
b10 L
1-
#290000
0-
#295000
b1 x
b1 f
1'
b10000000000000000000000000100 *
b10000000000000000000000000100 E
b10000000000000000000000000100 c
b10000000000000000000000000100 w
1-
#300000
0-
#305000
1(
b10000000000000001001001100000 )
b10000000000000001001001100000 D
b10000000000000001001001100000 ^
b10000000000000001001001100000 z
1-
#310000
0-
#315000
b10 f
0'
1(
1-
#320000
0-
#325000
b1 l
0(
b11 f
1<
0:
09
b10000000000000001 @
b10000000000000001 d
b10000000000000001 j
b1 ;
b1 e
b1 k
1-
#330000
0-
#335000
1G
0Z
b10000000000000001000000000000 5
b10000000000000001000000000000 N
b10000000000000001 6
b10000000000000001 O
b10000000000000001 r
17
b1 t
b0 f
1A
0<
1-
#340000
0-
#345000
0\
b1 L
b1 f
1'
0A
1-
#350000
0-
#355000
b0 L
1#
b10000000000000001000000000000 %
b10000000000000001000000000000 K
1(
1-
#360000
0-
#365000
1(
0#
b10 f
0'
1-
#370000
0-
#375000
b11 f
1<
0(
b0 |
b10000000000000 }
1-
#380000
0-
#385000
1Z
b10 m
b0 5
b0 N
b0 6
b0 O
b0 r
07
b0 t
0G
b10 4
b10 ]
b10 h
b0 f
1A
0<
1.
b0 ,
b0 2
b0 U
b10000000000000 1
b10000000000000 3
1-
#390000
0-
#395000
0A
b1 L
0.
1-
#400000
0-
#405000
1\
b10 L
1-
#410000
0-
#415000
b10 x
b1 f
1'
b10000000000000000000000001000 *
b10000000000000000000000001000 E
b10000000000000000000000001000 c
b10000000000000000000000001000 w
1-
#420000
0-
#425000
1(
b10000000000000010001111000000 )
b10000000000000010001111000000 D
b10000000000000010001111000000 ^
b10000000000000010001111000000 z
1-
#430000
0-
#435000
b10 f
0'
1(
1-
#440000
0-
#445000
0(
b11 f
1&
1-
#450000
0-
#455000
b0 f
1A
1-
#460000
0-
#465000
0\
b1 L
b1 f
1'
0&
0A
1-
#470000
0-
#475000
1\
b10 L
1(
1-
#480000
0-
#485000
1(
b10 f
0'
1-
#490000
0-
#495000
b11 f
1&
0(
b11000000000000 }
1-
#500000
0-
#505000
b11 m
b11 4
b11 ]
b11 h
b0 f
1A
1.
b11000000000000 1
b11000000000000 3
1-
#510000
0-
#515000
b11 x
b1 f
1'
b10000000000000000000000001100 *
b10000000000000000000000001100 E
b10000000000000000000000001100 c
b10000000000000000000000001100 w
0&
0A
0\
b1 L
0.
1-
#520000
0-
#525000
1(
b10000000000000011000111100000 )
b10000000000000011000111100000 D
b10000000000000011000111100000 ^
b10000000000000011000111100000 z
1\
b10 L
1-
#530000
0-
#535000
b10 f
0'
1(
1-
#540000
0-
#545000
b11 l
0(
b11 f
1<
1:
19
0>
b10000000000000011 @
b10000000000000011 d
b10000000000000011 j
b11 ;
b11 e
b11 k
1-
#550000
0-
#555000
1G
0Z
b10000000000000011000000000000 5
b10000000000000011000000000000 N
b10000000000000011 6
b10000000000000011 O
b10000000000000011 r
17
b1 t
b0 f
1A
0<
1-
#560000
0-
#565000
0\
b1 L
b1 f
1'
0A
1-
#570000
0-
#575000
b0 L
1#
b10000000000000011000000000000 %
b10000000000000011000000000000 K
1(
1-
#580000
0-
#585000
1(
0#
b10 f
0'
1-
#590000
0-
#595000
b11 f
1<
0(
1-
#600000
0-
#605000
b10000000000000011000000000000 5
b10000000000000011000000000000 N
b10000000000000011 6
b10000000000000011 O
b10000000000000011 r
b11 t
b0 f
1A
0<
1-
#610000
0-
#615000
0A
0~
1-
#620000
0-
#625000
1G
1.
00
1-
